sparkback/__init__.py
sparkback/spark.py
sparkback-0.3.0.dist-info/METADATA
sparkback-0.3.0.dist-info/WHEEL
sparkback-0.3.0.dist-info/entry_points.txt
sparkback-0.3.0.dist-info/licenses/LICENSE.txt
sparkback-0.3.0.dist-info/RECORD
