Metadata-Version: 2.4
Name: sparkback
Version: 0.3.0
Summary: Sparklines Library
Project-URL: Homepage, https://github.com/mmichie/sparkback
Author-email: Matt Michie <mmichie@gmail.com>
License: MIT
License-File: LICENSE.txt
Classifier: Development Status :: 3 - Alpha
Classifier: Intended Audience :: Developers
Classifier: License :: OSI Approved :: MIT License
Classifier: Programming Language :: Python
Classifier: Programming Language :: Python :: 3
Classifier: Programming Language :: Python :: 3.8
Classifier: Topic :: Software Development :: Libraries
Requires-Python: >=3.8.1
Requires-Dist: psutil>=7.2.0
Requires-Dist: requests>=2.31.0
Provides-Extra: dev
Requires-Dist: black<25.0,>=23.7; extra == 'dev'
Requires-Dist: flake8<8.0,>=6.1; extra == 'dev'
Requires-Dist: pylint<4.0.0,>=2.17.5; extra == 'dev'
Requires-Dist: pytest<9.0,>=7.4; extra == 'dev'
